<?xml version="1.0" encoding="UTF-8"?>
<!DOCTYPE batch SYSTEM "file:/homes/gws/sang/bayes/samiam/batchtool15/batchquery.dtd">
<batch>
	<query network="/homes/gws/sang/test/BN/toy-qmr/or-qmr/small-60/or-60-20-6.dne">
		<probability algorithm="recursiveconditioning">
			<evidence>
				<id>c_15</id>
				<state>true</state>
			</evidence>
			<evidence>
				<id>c_33</id>
				<state>true</state>
			</evidence>
			<evidence>
				<id>c_57</id>
				<state>true</state>
			</evidence>
			<evidence>
				<id>c_11</id>
				<state>true</state>
			</evidence>
			<evidence>
				<id>c_45</id>
				<state>true</state>
			</evidence>
			<evidence>
				<id>c_56</id>
				<state>true</state>
			</evidence>
			<evidence>
				<id>c_2</id>
				<state>true</state>
			</evidence>
			<evidence>
				<id>c_4</id>
				<state>true</state>
			</evidence>
			<evidence>
				<id>c_39</id>
				<state>true</state>
			</evidence>
			<evidence>
				<id>c_5</id>
				<state>true</state>
			</evidence>
			<evidence>
				<id>c_53</id>
				<state>true</state>
			</evidence>
			<evidence>
				<id>c_58</id>
				<state>true</state>
			</evidence>
			<evidence>
				<id>c_12</id>
				<state>true</state>
			</evidence>
			<evidence>
				<id>c_31</id>
				<state>true</state>
			</evidence>
			<evidence>
				<id>c_60</id>
				<state>false</state>
			</evidence>
			<evidence>
				<id>c_26</id>
				<state>false</state>
			</evidence>
			<evidence>
				<id>c_48</id>
				<state>false</state>
			</evidence>
			<evidence>
				<id>c_20</id>
				<state>true</state>
			</evidence>
			<evidence>
				<id>c_35</id>
				<state>true</state>
			</evidence>
			<evidence>
				<id>c_55</id>
				<state>false</state>
			</evidence>
			<evidence>
				<id>c_21</id>
				<state>false</state>
			</evidence>
			<evidence>
				<id>c_10</id>
				<state>false</state>
			</evidence>
			<evidence>
				<id>c_18</id>
				<state>false</state>
			</evidence>
			<evidence>
				<id>p_32</id>
				<state>false</state>
			</evidence>
			<evidence>
				<id>p_2</id>
				<state>false</state>
			</evidence>
			<evidence>
				<id>p_44</id>
				<state>false</state>
			</evidence>
			<evidence>
				<id>p_49</id>
				<state>false</state>
			</evidence>
			<evidence>
				<id>p_8</id>
				<state>false</state>
			</evidence>
			<evidence>
				<id>p_50</id>
				<state>false</state>
			</evidence>
			<evidence>
				<id>p_17</id>
				<state>false</state>
			</evidence>
			<evidence>
				<id>p_27</id>
				<state>false</state>
			</evidence>
			<evidence>
				<id>p_20</id>
				<state>false</state>
			</evidence>
			<evidence>
				<id>p_21</id>
				<state>false</state>
			</evidence>
			<evidence>
				<id>p_52</id>
				<state>false</state>
			</evidence>
			<evidence>
				<id>p_42</id>
				<state>false</state>
			</evidence>
			<evidence>
				<id>p_55</id>
				<state>false</state>
			</evidence>
			<evidence>
				<id>p_30</id>
				<state>false</state>
			</evidence>
			<evidence>
				<id>p_19</id>
				<state>false</state>
			</evidence>
			<evidence>
				<id>p_15</id>
				<state>false</state>
			</evidence>
			<evidence>
				<id>p_7</id>
				<state>false</state>
			</evidence>
			<evidence>
				<id>p_57</id>
				<state>false</state>
			</evidence>
			<evidence>
				<id>p_37</id>
				<state>false</state>
			</evidence>
			<evidence>
				<id>p_18</id>
				<state>false</state>
			</evidence>
			<evidence>
				<id>p_11</id>
				<state>false</state>
			</evidence>
			<evidence>
				<id>p_13</id>
				<state>false</state>
			</evidence>
			<evidence>
				<id>p_54</id>
				<state>true</state>
			</evidence>
			<evidence>
				<id>c_8</id>
				<state>true</state>
			</evidence>
			<evidence>
				<id>c_19</id>
				<state>true</state>
			</evidence>
		</probability>
	</query>
</batch>

